Metadata-Version: 1.1
Name: epika-python3
Version: 0.9.14
Summary: echinopsii Pika Python AMQP Client Library
Home-page: https://github.com/echinopsii/net.echinopsii.3rdparty.pika
Author: Mathilde Ffrench
Author-email: mathilde.ffrench@echinopsii.net
License: MPL v2.0
Download-URL: https://github.com/echinopsii/net.echinopsii.3rdparty.pika/tarball/e-p3-0.9.14
Platform: UNKNOWN
Classifier: Development Status :: 5 - Production/Stable
Classifier: Intended Audience :: Developers
Classifier: License :: OSI Approved :: GNU General Public License (GPL)
Classifier: License :: OSI Approved :: Mozilla Public License 1.1 (MPL 1.1)
Classifier: Natural Language :: English
Classifier: Operating System :: OS Independent
Classifier: Programming Language :: Python :: 3.2
Classifier: Programming Language :: Python :: Implementation :: CPython
Classifier: Topic :: Communications
Classifier: Topic :: Internet
Classifier: Topic :: Software Development :: Libraries
Classifier: Topic :: Software Development :: Libraries :: Python Modules
Classifier: Topic :: System :: Networking
